{"userId":"U1001","avgTimeBtwnVisitsInHours":2.706423611111111}
{"userId":"U1002","avgTimeBtwnVisitsInHours":2.285357142857143}
{"userId":"U1003","avgTimeBtwnVisitsInHours":1.9605555555555556}
{"userId":"U1004","avgTimeBtwnVisitsInHours":3.442083333333333}
{"userId":"U1005","avgTimeBtwnVisitsInHours":2.346626984126984}
{"userId":"U1006","avgTimeBtwnVisitsInHours":2.480493827160494}
{"userId":"U1007","avgTimeBtwnVisitsInHours":2.547420634920635}
{"userId":"U1008","avgTimeBtwnVisitsInHours":2.8857291666666667}
{"userId":"U1009","avgTimeBtwnVisitsInHours":2.696076388888889}
{"userId":"U1010","avgTimeBtwnVisitsInHours":3.3023809523809526}
{"userId":"U1011","avgTimeBtwnVisitsInHours":5.135138888888889}
{"userId":"U1012","avgTimeBtwnVisitsInHours":6.8687962962962965}
{"userId":"U1013","avgTimeBtwnVisitsInHours":2.3192708333333334}
{"userId":"U1014","avgTimeBtwnVisitsInHours":2.3772569444444445}
{"userId":"U1015","avgTimeBtwnVisitsInHours":3.206166666666667}
{"userId":"U1016","avgTimeBtwnVisitsInHours":2.0049242424242424}
{"userId":"U1017","avgTimeBtwnVisitsInHours":4.589027777777778}
{"userId":"U1018","avgTimeBtwnVisitsInHours":2.1464583333333334}
{"userId":"U1019","avgTimeBtwnVisitsInHours":2.7375}
{"userId":"U1020","avgTimeBtwnVisitsInHours":6.344305555555556}
{"userId":"U1021","avgTimeBtwnVisitsInHours":6.399583333333333}
{"userId":"U1022","avgTimeBtwnVisitsInHours":2.112694444444444}
{"userId":"U1023","avgTimeBtwnVisitsInHours":6.8654166666666665}
{"userId":"U1024","avgTimeBtwnVisitsInHours":1.5341111111111112}
{"userId":"U1025","avgTimeBtwnVisitsInHours":1.9267283950617284}
{"userId":"U1026","avgTimeBtwnVisitsInHours":4.4158333333333335}
{"userId":"U1027","avgTimeBtwnVisitsInHours":2.2509027777777777}
{"userId":"U1028","avgTimeBtwnVisitsInHours":2.582666666666667}
{"userId":"U1029","avgTimeBtwnVisitsInHours":3.0709920634920636}
{"userId":"U1030","avgTimeBtwnVisitsInHours":4.1425}
{"userId":"U1031","avgTimeBtwnVisitsInHours":3.535833333333333}
{"userId":"U1032","avgTimeBtwnVisitsInHours":2.5171180555555557}
{"userId":"U1033","avgTimeBtwnVisitsInHours":2.3680246913580247}
{"userId":"U1034","avgTimeBtwnVisitsInHours":3.9235}
{"userId":"U1035","avgTimeBtwnVisitsInHours":2.377388888888889}
{"userId":"U1036","avgTimeBtwnVisitsInHours":1.7939141414141413}
{"userId":"U1037","avgTimeBtwnVisitsInHours":2.3941666666666666}
{"userId":"U1038","avgTimeBtwnVisitsInHours":5.101944444444444}
{"userId":"U1039","avgTimeBtwnVisitsInHours":5.168611111111111}
{"userId":"U1040","avgTimeBtwnVisitsInHours":4.4743055555555555}
{"userId":"U1041","avgTimeBtwnVisitsInHours":2.7241666666666666}
{"userId":"U1042","avgTimeBtwnVisitsInHours":4.402708333333333}
{"userId":"U1043","avgTimeBtwnVisitsInHours":2.9030555555555555}
{"userId":"U1044","avgTimeBtwnVisitsInHours":4.187314814814815}
{"userId":"U1045","avgTimeBtwnVisitsInHours":2.572951388888889}
{"userId":"U1046","avgTimeBtwnVisitsInHours":2.5522619047619046}
{"userId":"U1047","avgTimeBtwnVisitsInHours":7.256666666666667}
{"userId":"U1048","avgTimeBtwnVisitsInHours":3.0091666666666668}
{"userId":"U1049","avgTimeBtwnVisitsInHours":2.175634920634921}
{"userId":"U1050","avgTimeBtwnVisitsInHours":2.1908333333333334}
{"userId":"U1051","avgTimeBtwnVisitsInHours":4.928333333333334}
{"userId":"U1052","avgTimeBtwnVisitsInHours":1.1108333333333333}
{"userId":"U1053","avgTimeBtwnVisitsInHours":2.628784722222222}
{"userId":"U1054","avgTimeBtwnVisitsInHours":2.3888541666666665}
{"userId":"U1055","avgTimeBtwnVisitsInHours":1.9957716049382714}
{"userId":"U1056","avgTimeBtwnVisitsInHours":3.110674603174603}
{"userId":"U1057","avgTimeBtwnVisitsInHours":2.3394444444444447}
{"userId":"U1058","avgTimeBtwnVisitsInHours":2.4658333333333333}
{"userId":"U1059","avgTimeBtwnVisitsInHours":2.3119444444444444}
{"userId":"U1060","avgTimeBtwnVisitsInHours":3.6096296296296293}
{"userId":"U1061","avgTimeBtwnVisitsInHours":1.3876851851851852}
{"userId":"U1062","avgTimeBtwnVisitsInHours":2.2310069444444443}
{"userId":"U1063","avgTimeBtwnVisitsInHours":2.7950694444444446}
{"userId":"U1064","avgTimeBtwnVisitsInHours":4.350740740740741}
{"userId":"U1065","avgTimeBtwnVisitsInHours":3.664375}
{"userId":"U1066","avgTimeBtwnVisitsInHours":4.427847222222222}
{"userId":"U1067","avgTimeBtwnVisitsInHours":5.604166666666667}
{"userId":"U1068","avgTimeBtwnVisitsInHours":2.881706349206349}
{"userId":"U1069","avgTimeBtwnVisitsInHours":2.930873015873016}
{"userId":"U1070","avgTimeBtwnVisitsInHours":6.1443055555555555}
{"userId":"U1071","avgTimeBtwnVisitsInHours":2.5229166666666667}
{"userId":"U1072","avgTimeBtwnVisitsInHours":1.5790277777777777}
{"userId":"U1073","avgTimeBtwnVisitsInHours":2.7343055555555558}
{"userId":"U1074","avgTimeBtwnVisitsInHours":6.880416666666667}
{"userId":"U1075","avgTimeBtwnVisitsInHours":1.8958080808080808}
{"userId":"U1076","avgTimeBtwnVisitsInHours":11.130555555555556}
{"userId":"U1077","avgTimeBtwnVisitsInHours":4.368680555555556}
{"userId":"U1078","avgTimeBtwnVisitsInHours":2.3403472222222224}
{"userId":"U1079","avgTimeBtwnVisitsInHours":8.526944444444444}
{"userId":"U1080","avgTimeBtwnVisitsInHours":4.724722222222222}
{"userId":"U1081","avgTimeBtwnVisitsInHours":2.622283950617284}
{"userId":"U1082","avgTimeBtwnVisitsInHours":3.069325396825397}
{"userId":"U1083","avgTimeBtwnVisitsInHours":5.438541666666667}
{"userId":"U1084","avgTimeBtwnVisitsInHours":2.244479166666667}
{"userId":"U1085","avgTimeBtwnVisitsInHours":2.2044444444444444}
{"userId":"U1086","avgTimeBtwnVisitsInHours":1.8178819444444445}
{"userId":"U1087","avgTimeBtwnVisitsInHours":2.9832870370370372}
{"userId":"U1088","avgTimeBtwnVisitsInHours":2.2253611111111113}
{"userId":"U1089","avgTimeBtwnVisitsInHours":1.9930050505050505}
{"userId":"U1090","avgTimeBtwnVisitsInHours":2.772936507936508}
{"userId":"U1091","avgTimeBtwnVisitsInHours":2.3568650793650794}
{"userId":"U1092","avgTimeBtwnVisitsInHours":2.361222222222222}
{"userId":"U1093","avgTimeBtwnVisitsInHours":3.2666203703703705}
{"userId":"U1094","avgTimeBtwnVisitsInHours":3.892175925925926}
{"userId":"U1095","avgTimeBtwnVisitsInHours":2.2229513888888888}
{"userId":"U1096","avgTimeBtwnVisitsInHours":2.198611111111111}
{"userId":"U1097","avgTimeBtwnVisitsInHours":2.1266666666666665}
{"userId":"U1098","avgTimeBtwnVisitsInHours":1.9248611111111111}
{"userId":"U1099","avgTimeBtwnVisitsInHours":2.4340432098765428}
{"userId":"U1100","avgTimeBtwnVisitsInHours":3.8609444444444443}
{"userId":"U1101","avgTimeBtwnVisitsInHours":2.217619047619048}
{"userId":"U1102","avgTimeBtwnVisitsInHours":6.139166666666667}
{"userId":"U1103","avgTimeBtwnVisitsInHours":2.893111111111111}
{"userId":"U1104","avgTimeBtwnVisitsInHours":1.968207070707071}
{"userId":"U1105","avgTimeBtwnVisitsInHours":3.499388888888889}
{"userId":"U1106","avgTimeBtwnVisitsInHours":1.514642857142857}
{"userId":"U1107","avgTimeBtwnVisitsInHours":1.8825}
{"userId":"U1108","avgTimeBtwnVisitsInHours":2.7034375}
{"userId":"U1109","avgTimeBtwnVisitsInHours":2.558576388888889}
{"userId":"U1110","avgTimeBtwnVisitsInHours":8.157361111111111}
{"userId":"U1111","avgTimeBtwnVisitsInHours":2.163641975308642}
{"userId":"U1112","avgTimeBtwnVisitsInHours":2.363805555555556}
{"userId":"U1113","avgTimeBtwnVisitsInHours":3.041904761904762}
{"userId":"U1114","avgTimeBtwnVisitsInHours":2.3649074074074075}
{"userId":"U1115","avgTimeBtwnVisitsInHours":2.705079365079365}
{"userId":"U1116","avgTimeBtwnVisitsInHours":2.548703703703704}
{"userId":"U1117","avgTimeBtwnVisitsInHours":3.869944444444444}
{"userId":"U1118","avgTimeBtwnVisitsInHours":3.357277777777778}
{"userId":"U1119","avgTimeBtwnVisitsInHours":7.810972222222222}
{"userId":"U1120","avgTimeBtwnVisitsInHours":2.3538194444444445}
{"userId":"U1121","avgTimeBtwnVisitsInHours":10.300833333333333}
{"userId":"U1122","avgTimeBtwnVisitsInHours":2.2919722222222223}
{"userId":"U1123","avgTimeBtwnVisitsInHours":3.738125}
{"userId":"U1124","avgTimeBtwnVisitsInHours":3.168425925925926}
{"userId":"U1125","avgTimeBtwnVisitsInHours":2.2153888888888886}
{"userId":"U1126","avgTimeBtwnVisitsInHours":3.6071296296296294}
{"userId":"U1127","avgTimeBtwnVisitsInHours":5.065740740740741}
{"userId":"U1128","avgTimeBtwnVisitsInHours":2.19375}
{"userId":"U1129","avgTimeBtwnVisitsInHours":8.730277777777777}
{"userId":"U1130","avgTimeBtwnVisitsInHours":6.658472222222223}
{"userId":"U1131","avgTimeBtwnVisitsInHours":6.138981481481481}
{"userId":"U1132","avgTimeBtwnVisitsInHours":3.919722222222222}
{"userId":"U1133","avgTimeBtwnVisitsInHours":1.7269444444444444}
{"userId":"U1134","avgTimeBtwnVisitsInHours":1.1687896825396824}
{"userId":"U1135","avgTimeBtwnVisitsInHours":1.799837962962963}
{"userId":"U1136","avgTimeBtwnVisitsInHours":2.3796875}
{"userId":"U1137","avgTimeBtwnVisitsInHours":2.3472500000000003}
{"userId":"U1138","avgTimeBtwnVisitsInHours":5.313055555555556}
